LICENSE.txt
README.md
requirements.txt
setup.py
teste.py
BBFdocs/mkdocs.yml
BBFdocs/docs/index.md
BBFdocs/site/404.html
BBFdocs/site/index.html
BBFdocs/site/sitemap.xml
BBFdocs/site/sitemap.xml.gz
BBFdocs/site/css/base.css
BBFdocs/site/css/base.min.css
BBFdocs/site/css/bootstrap-custom.css
BBFdocs/site/css/bootstrap-custom.min.css
BBFdocs/site/css/cinder.css
BBFdocs/site/css/cinder.min.css
BBFdocs/site/css/highlight.css
BBFdocs/site/css/highlight.min.css
BBFdocs/site/fonts/fontawesome-webfont.eot
BBFdocs/site/fonts/fontawesome-webfont.svg
BBFdocs/site/fonts/fontawesome-webfont.ttf
BBFdocs/site/fonts/fontawesome-webfont.woff
BBFdocs/site/img/favicon.ico
BBFdocs/site/img/grid1.png
BBFdocs/site/img/grid10.png
BBFdocs/site/img/grid11.png
BBFdocs/site/img/grid12.png
BBFdocs/site/img/grid13.png
BBFdocs/site/img/grid14.png
BBFdocs/site/img/grid15.png
BBFdocs/site/img/grid16.png
BBFdocs/site/img/grid17.png
BBFdocs/site/img/grid18.png
BBFdocs/site/img/grid19.png
BBFdocs/site/img/grid2.png
BBFdocs/site/img/grid20.png
BBFdocs/site/img/grid3.png
BBFdocs/site/img/grid4.png
BBFdocs/site/img/grid5.png
BBFdocs/site/img/grid6.png
BBFdocs/site/img/grid7.png
BBFdocs/site/img/grid8.png
BBFdocs/site/img/grid9.png
BBFdocs/site/js/base.js
BBFdocs/site/js/bootstrap-3.0.3.min.js
BBFdocs/site/js/highlight.pack.js
BBFdocs/site/search/lunr.js
BBFdocs/site/search/main.js
BBFdocs/site/search/search_index.json
BBFdocs/site/search/worker.js
BBFinance/BBFinance.py
BBFinance/__init__.py
BBFinance.egg-info/PKG-INFO
BBFinance.egg-info/SOURCES.txt
BBFinance.egg-info/dependency_links.txt
BBFinance.egg-info/requires.txt
BBFinance.egg-info/top_level.txt
BBFinance/__pycache__/BBFinance.cpython-311.pyc
BBFinance/__pycache__/BBFinance.cpython-39.pyc
BBFinance/__pycache__/__init__.cpython-311.pyc
BBFinance/__pycache__/__init__.cpython-39.pyc
Banco/DataClients.db
__pycache__/__init__.cpython-39.pyc
__pycache__/main.cpython-39.pyc
docs/CNAME