Metadata-Version: 2.1
Name: BBFinance
Version: 1.5.2
Summary: Uma biblioteca com o objetivo de adquirir informações de ações do mercado financeiro de maneira rápida e prática, afim de incluir todos no mercado
Home-page: https://github.com/beb0pp/BBFinance
Author: Luis Abreu
Author-email: luss.fel@gmail.com
License: GPLv3
Classifier: Development Status :: 3 - Alpha
Classifier: Intended Audience :: Developers
Classifier: License :: OSI Approved :: GNU General Public License v3 (GPLv3)
Classifier: Programming Language :: Python :: 3.9
License-File: LICENSE.txt
